TK_log/TK.py
TK_log/__init__.py
TK_log-0.0.1.dist-info/LICENSE
TK_log-0.0.1.dist-info/METADATA
TK_log-0.0.1.dist-info/WHEEL
TK_log-0.0.1.dist-info/top_level.txt
TK_log-0.0.1.dist-info/RECORD
