Metadata-Version: 2.1
Name: TK-log
Version: 0.0.1
Summary: Package to log user activity
Home-page: 
Author: ravi
Author-email: ravi.masna@talentkind.com
License: MIT
Platform: UNKNOWN
Requires-Python: >=3.9
License-File: LICENSE
